hack4u/__init__.py
hack4u/courses.py
hack4u/utils.py
lu1nv-0.1.1.dist-info/METADATA
lu1nv-0.1.1.dist-info/WHEEL
lu1nv-0.1.1.dist-info/top_level.txt
lu1nv-0.1.1.dist-info/RECORD
