Metadata-Version: 2.4
Name: Lu1nv
Version: 0.1.1
Summary: Hola Solecito, prueba #2 para decirte te amoou. 
Home-page: https://hack4u.io
Author: Luis E Martinez
Dynamic: author
Dynamic: description
Dynamic: description-content-type
Dynamic: home-page
Dynamic: summary
